{
	"miniprogramRoot": "dist/",
	"description": "项目配置文件。",
	"setting": {
		"urlCheck": false,
		"es6": false,
		"enhance": false,
		"postcss": true,
		"minified": true,
		"newFeature": true,
		"coverView": true,
		"autoAudits": false,
		"uglifyFileName": false,
		"checkInvalidKey": true,
		"checkSiteMap": true,
		"uploadWithSourceMap": true,
		"babelSetting": {
			"ignore": [],
			"disablePlugins": [],
			"outputPath": ""
		}
	},
	"appid": "wxfdf974e694597f4e",
	"projectname": "%E6%99%BA%E9%9A%9C%E4%BA%8C%E7%99%BE%E4%BA%94",
	"simulatorType": "wechat",
	"simulatorPluginLibVersion": {},
	"libVersion": "2.7.4",
	"cloudfunctionRoot": "functions/",
	"condition": {
		"search": {
			"current": -1,
			"list": []
		},
		"conversation": {
			"current": -1,
			"list": []
		},
		"plugin": {
			"current": -1,
			"list": []
		},
		"game": {
			"list": []
		},
		"miniprogram": {
			"current": 0,
			"list": [
				{
					"id": -1,
					"name": "垃圾分类",
					"pathName": "pages/laji/index"
				}
			]
		}
	}
}